optik/__init__.py
optik/common/__init__.py
optik/common/abi.py
optik/common/exceptions.py
optik/common/logger.py
optik/common/util.py
optik/common/world.py
optik/corpus/__init__.py
optik/corpus/__main__.py
optik/corpus/generator.py
optik/coverage/__init__.py
optik/coverage/coverage.py
optik/coverage/inst_coverage.py
optik/coverage/path_coverage.py
optik/dataflow/__init__.py
optik/dataflow/dataflow.py
optik/echidna/__init__.py
optik/echidna/__main__.py
optik/echidna/display.py
optik/echidna/interface.py
optik/echidna/runner.py
optik_tools-0.0.2.dist-info/LICENCE
optik_tools-0.0.2.dist-info/METADATA
optik_tools-0.0.2.dist-info/WHEEL
optik_tools-0.0.2.dist-info/entry_points.txt
optik_tools-0.0.2.dist-info/top_level.txt
optik_tools-0.0.2.dist-info/RECORD
