Metadata-Version: 2.1
Name: optik-tools
Version: 0.0.2
Summary: Symbolic execution toolkit for Ethereum smart-contracts
Author: Trail of Bits
Requires-Python: >=3.7
License-File: LICENCE
Requires-Dist: setuptools (>=45)
Requires-Dist: wheel
Requires-Dist: pymaat (>=0.6.7)
Requires-Dist: eth-abi
Requires-Dist: pysha3
Requires-Dist: rlp
Requires-Dist: crytic-compile
Requires-Dist: slither-analyzer
Requires-Dist: solc-select
Requires-Dist: pyyaml
Provides-Extra: lint
Requires-Dist: black (~=22.0) ; extra == 'lint'
Provides-Extra: tests
Requires-Dist: pytest ; extra == 'tests'
